{
  "classes": {
    "Titan": 3111577790,
    "Hunter": 2271680882,
    "Warlock": 2271680883
  },
  "subclasses": {
    "prismatic_titan": 392767114,
    "prismatic_hunter": 392767115,
    "prismatic_warlock": 392767116,
    "solar_warlock": 3481416235,
    "arc_warlock": 2328211300,
    "void_warlock": 2849050827,
    "stasis_warlock": 3291545503,
    "strand_warlock": 242419885,
    "solar_titan": 2550323932,
    "arc_titan": 2932390016,
    "void_titan": 2842471112,
    "stasis_titan": 613647804,
    "strand_titan": 242419886,
    "solar_hunter": 2240888816,
    "arc_hunter": 2328211301,
    "void_hunter": 2453351420,
    "stasis_hunter": 873720784,
    "strand_hunter": 242419887
  },
  "aspects": {
    "Touch of Flame": 3534133814,
    "Heat Rises": 3887948515,
    "Icarus Dash": 3920911077,
    "Electrostatic Mind": 666015010,
    "Arc Soul": 3455326672,
    "Lightning Surge": 2812326428,
    "Feed the Void": 3520001075,
    "Child of the Old Gods": 1265663502,
    "Chaos Accelerant": 3128594062,
    "Bleak Watcher": 1835396609,
    "Iceflare Bolts": 3406135668,
    "Glacial Harvest": 3664831848,
    "Frostpulse": 645252611,
    "Mindspun Invocation": 2945379383,
    "Weaver's Call": 1248922835,
    "The Wanderer": 526786935,
    "Knockout": 2878280375,
    "Touch of Thunder": 2999301420,
    "Juggernaut": 952720860,
    "Thruster": 2942954611,
    "Controlled Demolition": 881358638,
    "Offensive Bulwark": 4080008252,
    "Bastion": 3941232607,
    "Sol Invictus": 3239662063,
    "Roaring Flames": 4294081309,
    "Consecration": 3326771373,
    "Tectonic Harvest": 3286116114,
    "Howl of the Storm": 1300957032,
    "Cryoclasm": 2885450812,
    "Diamond Lance": 1033372589,
    "Into the Fray": 2518261993,
    "Flechette Storm": 3038875349,
    "Drengr's Lash": 3722966925,
    "Banner of War": 2561679841,
    "Knock 'Em Down": 2713238943,
    "Gunpowder Gamble": 3656860190,
    "On Your Mark": 1576986092,
    "Flow State": 950424056,
    "Tempest Strike": 2671476649,
    "Lethal Current": 534011939,
    "Trapper's Ambush": 1528071617,
    "Stylish Executioner": 2691426628,
    "Vanishing Step": 4081677776,
    "Grim Harvest": 2680164440,
    "Winter's Shroud": 177744861,
    "Touch of Winter": 1913262255,
    "Shatterdive": 3297936042,
    "Threaded Specter": 1196970193,
    "Widow's Silk": 1023831906,
    "Whirling Maelstrom": 1760850853,
    "Ensnaring Slam": 2991228770
  },
  "fragments": {
    "Ember of Torches": 2213715663,
    "Ember of Singeing": 3150988595,
    "Ember of Empyrean": 2978755495,
    "Ember of Resolve": 2724310375,
    "Ember of Char": 2745325755,
    "Ember of Solace": 1764340761,
    "Ember of Ashes": 1845396620,
    "Ember of Benevolence": 881358637,
    "Ember of Beams": 1764340762,
    "Ember of Wonder": 2724310376,
    "Ember of Combustion": 3150988596,
    "Ember of Eruption": 2978755496,
    "Spark of Amplitude": 534011940,
    "Spark of Beacons": 2671476650,
    "Spark of Brilliance": 950424057,
    "Spark of Discharge": 1576986093,
    "Spark of Feedback": 3656860191,
    "Spark of Frequency": 2713238944,
    "Spark of Haste": 2561679842,
    "Spark of Ions": 3722966926,
    "Spark of Magnitude": 3038875350,
    "Spark of Recharge": 2518261994,
    "Spark of Resistance": 1033372590,
    "Spark of Shock": 2885450813,
    "Spark of Volts": 1300957033,
    "Echo of Cessation": 3286116115,
    "Echo of Domineering": 3326771374,
    "Echo of Exchange": 4294081310,
    "Echo of Expulsion": 3239662064,
    "Echo of Harvest": 3941232608,
    "Echo of Instability": 4080008253,
    "Echo of Leeching": 881358639,
    "Echo of Obscurity": 2942954612,
    "Echo of Persistence": 952720861,
    "Echo of Provision": 2999301421,
    "Echo of Reprisal": 2878280376,
    "Echo of Remnants": 526786936,
    "Echo of Starvation": 1248922836,
    "Echo of Undermining": 2945379384,
    "Echo of Vigilance": 645252612,
    "Whisper of Bonds": 3664831849,
    "Whisper of Chains": 3406135669,
    "Whisper of Conduction": 1835396610,
    "Whisper of Durance": 3128594063,
    "Whisper of Fissures": 1265663503,
    "Whisper of Fractures": 3520001076,
    "Whisper of Hedrons": 2812326429,
    "Whisper of Hunger": 3455326673,
    "Whisper of Impetus": 666015011,
    "Whisper of Refraction": 3887948516,
    "Whisper of Rending": 3920911078,
    "Whisper of Rime": 3534133815,
    "Whisper of Shards": 2213715664,
    "Thread of Ascent": 2991228771,
    "Thread of Continuity": 1760850854,
    "Thread of Evolution": 1023831907,
    "Thread of Finality": 1196970194,
    "Thread of Fury": 3297936043,
    "Thread of Generation": 1913262256,
    "Thread of Isolation": 177744862,
    "Thread of Mind": 2680164441,
    "Thread of Propagation": 4081677777,
    "Thread of Rebirth": 2691426629,
    "Thread of Transmutation": 1528071618,
    "Thread of Warding": 534011941,
    "Thread of Wisdom": 2671476651,
    "Facet of Awakening": 123456789,
    "Facet of Balance": 123456790,
    "Facet of Blessing": 123456791,
    "Facet of Command": 123456792,
    "Facet of Courage": 123456793,
    "Facet of Dawn": 123456794,
    "Facet of Defiance": 123456795,
    "Facet of Devotion": 123456796,
    "Facet of Dominance": 123456797,
    "Facet of Grace": 123456798,
    "Facet of Hope": 123456799,
    "Facet of Honor": 123456800,
    "Facet of Justice": 123456801,
    "Facet of Mending": 123456802,
    "Facet of Protection": 123456803,
    "Facet of Purpose": 123456804,
    "Facet of Ruin": 123456805,
    "Facet of Sacrifice": 123456806,
    "Facet of Solitude": 123456807,
    "Facet of Strength": 123456808
  },
  "grenades": {
    "Solar Grenade": 3908463274,
    "Fusion Grenade": 3301268403,
    "Swarm Grenade": 4085636042,
    "Arcbolt Grenade": 3301268404,
    "Pulse Grenade": 3908463275,
    "Storm Grenade": 4085636043,
    "Vortex Grenade": 3301268405,
    "Scatter Grenade": 3908463276,
    "Axion Bolt": 4085636044,
    "Glacier Grenade": 3301268406,
    "Duskfield Grenade": 3908463277,
    "Coldsnap Grenade": 4085636045,
    "Grapple Grenade": 3301268407,
    "Shackle Grenade": 3908463278,
    "Threadling Grenade": 4085636046
  },
  "melees": {
    "Incinerator Snap": 1897393189,
    "Celestial Fire": 2765853264,
    "Pocket Singularity": 3623864812,
    "Chain Lightning": 1235168885,
    "Ball Lightning": 2345678901,
    "Penumbral Blast": 3456789012,
    "Arcane Needle": 4567890123,
    "Ballistic Slam": 5678901234,
    "Seismic Strike": 6789012345,
    "Frontal Assault": 7890123456,
    "Shield Throw": 8901234567,
    "Shield Bash": 9012345678,
    "Hammer Strike": 1234567890,
    "Throwing Hammer": 2345678902,
    "Shiver Strike": 3456789013,
    "Frenzied Blade": 4567890124,
    "Threaded Strike": 5678901235,
    "Weighted Knife": 6789012346,
    "Proximity Knife": 7890123457,
    "Combination Blow": 8901234568,
    "Disorienting Blow": 9012345679,
    "Lightning Surge Strike": 1234567891,
    "Snare Bomb": 2345678903,
    "Smoke Bomb": 3456789014,
    "Withering Blade": 4567890125,
    "Threaded Spike": 5678901236
  },
  "classAbilities": {
    "Healing Rift": 1319291826,
    "Empowering Rift": 2319291827,
    "Towering Barricade": 3319291828,
    "Rally Barricade": 4319291829,
    "Marksman's Dodge": 5319291830,
    "Gambler's Dodge": 6319291831
  },
  "supers": {
    "Well of Radiance": 2164260293,
    "Daybreak": 3481416234,
    "Nova Bomb": 2849050826,
    "Nova Warp": 3289589202,
    "Chaos Reach": 3168997075,
    "Stormtrance": 2328211299,
    "Winter's Wrath": 3291545502,
    "Needlestorm": 242419884,
    "Phoenix Dive": 392767113,
    "Ward of Dawn": 2842471111,
    "Sentinel Shield": 3382391785,
    "Twilight Arsenal": 2550323933,
    "Hammer of Sol": 2550323931,
    "Burning Maul": 3849796742,
    "Fist of Havoc": 2932390015,
    "Thundercrash": 2182324868,
    "Glacial Quake": 613647803,
    "Bladefury": 242419883,
    "Drengr's Lash Super": 392767112,
    "Golden Gun": 2240888815,
    "Blade Barrage": 4142383698,
    "Arc Staff": 2328211298,
    "Gathering Storm": 1617375317,
    "Storm's Edge": 3722966924,
    "Shadowshot": 2453351419,
    "Spectral Blades": 3887948514,
    "Silence and Squall": 873720783,
    "Silkstrike": 242419882,
    "Spirit of the Lyre": 392767111
  },
  "exotics": {
    "Wishful Ignorance": 953037313,
    "Ophidian Aspect": 1062353751,
    "Transversive Steps": 2275132880,
    "Crown of Tempests": 3381022971,
    "Nezarec's Sin": 2523259394,
    "Eye of Another World": 1458010786,
    "Verity's Brow": 3829285960,
    "Starfire Protocol": 1981675726,
    "Sunbracers": 1275480033,
    "Phoenix Protocol": 3156190639,
    "Lunafaction Boots": 2638324500,
    "Boots of the Assembler": 2638324501,
    "Osmiomancy Gloves": 1062353752,
    "Cenotaph Mask": 1458010787,
    "Swarmers": 1275480034,
    "Syntho ceps": 3573464984,
    "One-Eyed Mask": 2523259395,
    "Dunemarchers": 2275132881,
    "Lion Rampant": 1062353753,
    "Heart of Inmost Light": 3829285961,
    "Armamentarium": 1981675727,
    "Ashen Wake": 3156190640,
    "Phoenix Cradle": 2638324502,
    "Loreley Splendor Helm": 1458010788,
    "Hoarfrost-Z": 1275480035,
    "Point-Contact Cannon Brace": 3573464985,
    "Stoicism": 2523259396,
    "Celestial Nighthawk": 2275132882,
    "Star-Eater Scales": 1062353754,
    "Orpheus Rig": 3829285962,
    "Omnioculus": 1981675728,
    "Renewal Grasps": 3156190641,
    "Gyrfalcon's Hauberk": 2638324503,
    "Cyrtarachne's Facade": 1458010789,
    "Liar's Handshake": 1275480036,
    "Raiju's Harness": 3573464986,
    "Shinobu's Vow": 2523259397
  },
  "weapons": {
    "Hawkmoon": 3856705927,
    "Ace of Spades": 347366834,
    "The Last Word": 1364093401,
    "Thorn": 3164616407,
    "Witherhoard": 1357080535,
    "Izanagi's Burden": 3211806999,
    "Divinity": 4103414242,
    "Telesto": 2208405142,
    "Gjallarhorn": 1363886209,
    "Sleeper Simulant": 4036115577,
    "Whisper of the Worm": 1891561814,
    "Thunderlord": 3325463374,
    "Cloudstrike": 2903777146,
    "Touch of Malice": 3999354030,
    "Outbreak Perfected": 2628991617,
    "Osteo Striga": 46524085,
    "Trinity Ghoul": 814876685,
    "Le Monarque": 3588934839,
    "Ticuu's Divination": 3260753130,
    "Lorentz Driver": 3593598010
  },
  "mods": {
    "Font of Might": 2979815167,
    "Elemental Time Dilation": 2979815168,
    "Elemental Charge": 2979815169,
    "High-Energy Fire": 2979815170,
    "Charged Up": 2979815171,
    "Supercharged": 2979815172,
    "Protective Light": 2979815173,
    "Taking Charge": 2979815174,
    "Stacks on Stacks": 2979815175,
    "Well of Life": 2979815176,
    "Well of Tenacity": 2979815177,
    "Elemental Armaments": 2979815178,
    "Seeking Wells": 2979815179,
    "Elemental Ordnance": 2979815180,
    "Bountiful Wells": 2979815181,
    "Font of Wisdom": 2979815182,
    "Reaping Wellmaker": 2979815183,
    "Melee Wellmaker": 2979815184
  },
  "default": 1458010785
}
